code/__init__.py
ppyNotion-0.0.1.1.dist-info/LICENSE
ppyNotion-0.0.1.1.dist-info/METADATA
ppyNotion-0.0.1.1.dist-info/WHEEL
ppyNotion-0.0.1.1.dist-info/top_level.txt
ppyNotion-0.0.1.1.dist-info/RECORD
